python_weaver-0.1.6.dist-info/licenses/LICENSE
weaver/__init__.py
weaver/agent.py
weaver/blueprint.py
weaver/cli.py
weaver/config.py
weaver/exceptions.py
weaver/project.py
weaver/connectors/__init__.py
weaver/connectors/base_connector.py
weaver/connectors/pdf_reader.py
weaver/connectors/url_scraper.py
python_weaver-0.1.6.dist-info/METADATA
python_weaver-0.1.6.dist-info/WHEEL
python_weaver-0.1.6.dist-info/entry_points.txt
python_weaver-0.1.6.dist-info/top_level.txt
python_weaver-0.1.6.dist-info/RECORD
